{
    "asansCardList": [
        11
    ],
    "asansCardData": {
        "11": {
            "id": 11,
            "labelCard": "Yogla для начинающих",
            "descriptionCard": "Набор упражнений для тех кто только начал практиковать йогу.",
            "previewCard": "assets/img/yoga-beginner.jpg",
            "complexityCard": "hard",
            "totalTimeCard": 25,
            "asans": [
                {
                    "id": 21,
                    "delayAsan": 5000
                },
                {
                    "id": 22,
                    "delayAsan": 2000
                }
            ]
        }
    },
    "asansData": {
        "21": {
            "id": 21,
            "titleAsan": "Собака мордой вниз",
            "descriptionAsan": "Адхо Мукха Шванасана относится к позам йоги, снимающим усталость, возвращающим потерянную энергию. Она особенно полезна для бегунов, отдыхающих после забега.",
            "imageAsan": "https://s.hanuman.ru/files/imagecache/center_thumbnail_full/mukha_shvanasana_01_0.JPG",
            "iconAsan": "https://image.flaticon.com/icons/svg/84/84717.svg",
            "voiceAsan": "voice.mp3"
        },
        "22": {
            "id": 22,
            "titleAsan": "БХАРАДВАДЖАСАНА II",
            "descriptionAsan": "Бхарадваджасана II относится к упражнениям йоги для «среднего» уровня. Она развивает гибкость позвоночника, коленей и плеч и только для людей с эластичным позвоночником она не очень эффективна.",
            "imageAsan": "https://s.hanuman.ru/files/imagecache/center_thumbnail_full/II.jpg",
            "iconAsan": "https://image.flaticon.com/icons/svg/84/84717.svg",
            "voiceAsan": "voice.mp3"
        }
    }
}